latent_watermark/__init__.py
latent_watermark/_version.py
latent_watermark/cli.py
latent_watermark/config.py
latent_watermark/config_formatter.py
latent_watermark/config_validator.py
latent_watermark/default_config.yml
latent_watermark/file_utils.py
latent_watermark/models.py
latent_watermark/watermark.py
latent_watermark/watermark_utils.py
latent_watermark-0.1.0.dist-info/LICENSE
latent_watermark-0.1.0.dist-info/METADATA
latent_watermark-0.1.0.dist-info/WHEEL
latent_watermark-0.1.0.dist-info/entry_points.txt
latent_watermark-0.1.0.dist-info/top_level.txt
latent_watermark-0.1.0.dist-info/RECORD
