Metadata-Version: 2.1
Name: latent-watermark
Version: 0.1.0
Summary: A robust latent watermark system for tracking image distribution
Author-email: Cheng Yanru <yanru@cyanru.com>
License: MIT
Project-URL: Homepage, https://github.com/cyanru/latent-watermark
Project-URL: Repository, https://github.com/cyanru/latent-watermark
Project-URL: Documentation, https://github.com/cyanru/latent-watermark#readme
Keywords: watermark,image,security,tracking,latent
Classifier: Development Status :: 4 - Beta
Classifier: Intended Audience :: Developers
Classifier: License :: OSI Approved :: MIT License
Classifier: Programming Language :: Python :: 3
Classifier: Programming Language :: Python :: 3.8
Classifier: Programming Language :: Python :: 3.9
Classifier: Programming Language :: Python :: 3.10
Classifier: Programming Language :: Python :: 3.11
Classifier: Programming Language :: Python :: 3.12
Classifier: Topic :: Multimedia :: Graphics
Classifier: Topic :: Security
Requires-Python: >=3.8
License-File: LICENSE
Requires-Dist: pydantic>=2.0.0
Requires-Dist: pyyaml>=6.0
Requires-Dist: blind-watermark>=0.4.4
Requires-Dist: pillow>=9.0.0
Requires-Dist: numpy>=1.20.0
Provides-Extra: dev
Requires-Dist: pytest>=7.0.0; extra == "dev"
Requires-Dist: pytest-cov>=4.0.0; extra == "dev"
Requires-Dist: black>=23.0.0; extra == "dev"
Requires-Dist: isort>=5.0.0; extra == "dev"
Requires-Dist: mypy>=1.0.0; extra == "dev"
